{
   "asset" : {
      "generator" : "osg2cesiumApp",
      "version" : "1.0"
   },
   "root" : {
      "boundingVolume" : {
         "box" : [
            -20.417436599731445,
            -180.25,
            -103.26492309570313,
            19.207586288452148,
            0.0,
            0.0,
            0.0,
            18.875030517578125,
            0.0,
            0.0,
            0.0,
            7.315338134765625
         ]
      },
      "children" : [
         {
            "boundingVolume" : {
               "box" : [
                  -30.125,
                  -189.625,
                  -102.63301086425781,
                  9.4375114440917969,
                  0.0,
                  0.0,
                  0.0,
                  9.4375152587890625,
                  0.0,
                  0.0,
                  0.0,
                  5.0791816711425781
               ]
            },
            "content" : {
               "uri" : "Tile_+001_+001_L21_0003200.json"
            },
            "geometricError" : 0.70504790544509888
         },
         {
            "boundingVolume" : {
               "box" : [
                  -30.125,
                  -170.875,
                  -101.61383056640625,
                  9.4375114440917969,
                  0.0,
                  0.0,
                  0.0,
                  9.4375152587890625,
                  0.0,
                  0.0,
                  0.0,
                  4.6234092712402344
               ]
            },
            "content" : {
               "uri" : "Tile_+001_+001_L21_0003210.json"
            },
            "geometricError" : 0.70504790544509888
         },
         {
            "boundingVolume" : {
               "box" : [
                  -11.011180877685547,
                  -189.625,
                  -104.07964324951172,
                  9.80133056640625,
                  0.0,
                  0.0,
                  0.0,
                  9.4375152587890625,
                  0.0,
                  0.0,
                  0.0,
                  6.4891204833984375
               ]
            },
            "content" : {
               "uri" : "Tile_+001_+001_L21_0003220.json"
            },
            "geometricError" : 0.70504790544509888
         },
         {
            "boundingVolume" : {
               "box" : [
                  -11.011180877685547,
                  -170.875,
                  -101.24473571777344,
                  9.80133056640625,
                  0.0,
                  0.0,
                  0.0,
                  9.4375152587890625,
                  0.0,
                  0.0,
                  0.0,
                  5.3270835876464844
               ]
            },
            "content" : {
               "uri" : "Tile_+001_+001_L21_0003230.json"
            },
            "geometricError" : 0.70504790544509888
         }
      ],
      "content" : {
         "uri" : "Tile_+001_+001_L20_000320t3.b3dm"
      },
      "geometricError" : 1.4100958108901978
   }
}
