{
   "asset" : {
      "generator" : "osg2cesiumApp",
      "version" : "1.0"
   },
   "root" : {
      "boundingVolume" : {
         "box" : [
            -215.16094970703125,
            129.125,
            -99.506500244140625,
            11.682991027832031,
            0.0,
            0.0,
            0.0,
            9.4375152587890625,
            0.0,
            0.0,
            0.0,
            5.6035919189453125
         ]
      },
      "content" : {
         "uri" : "Tile_+000_+003_L21_0002110.b3dm"
      },
      "geometricError" : 0.71160793304443359
   }
}
