{
   "asset" : {
      "generator" : "osg2cesiumApp",
      "version" : "1.0"
   },
   "root" : {
      "boundingVolume" : {
         "box" : [
            28.302528381347656,
            -295.53668212890625,
            -92.887786865234375,
            31.092678070068359,
            0.0,
            0.0,
            0.0,
            22.326828002929688,
            0.0,
            0.0,
            0.0,
            11.745464324951172
         ]
      },
      "children" : [
         {
            "boundingVolume" : {
               "box" : [
                  30.695833206176758,
                  -295.53668212890625,
                  -92.735488891601563,
                  33.485980987548828,
                  0.0,
                  0.0,
                  0.0,
                  22.326828002929688,
                  0.0,
                  0.0,
                  0.0,
                  12.581771850585938
               ]
            },
            "content" : {
               "uri" : "Tile_+002_+000_L15_0.json"
            },
            "geometricError" : 133.89674377441406
         }
      ],
      "content" : {
         "uri" : "Tile_+002_+000.b3dm"
      },
      "geometricError" : 17120.2998046875
   }
}
