{
   "asset" : {
      "generator" : "osg2cesiumApp",
      "version" : "1.0"
   },
   "root" : {
      "boundingVolume" : {
         "box" : [
            73.0,
            100.99528503417969,
            -102.91060638427734,
            75.790145874023438,
            0.0,
            0.0,
            0.0,
            75.79486083984375,
            0.0,
            0.0,
            0.0,
            14.306259155273438
         ]
      },
      "children" : [
         {
            "boundingVolume" : {
               "box" : [
                  73.0,
                  100.99528503417969,
                  -102.78260803222656,
                  75.790145874023438,
                  0.0,
                  0.0,
                  0.0,
                  75.79486083984375,
                  0.0,
                  0.0,
                  0.0,
                  14.351478576660156
               ]
            },
            "content" : {
               "uri" : "Tile_+002_+003_L18_0000t3.json"
            },
            "geometricError" : 21.76591682434082
         }
      ],
      "content" : {
         "uri" : "Tile_+002_+003_L17_000.b3dm"
      },
      "geometricError" : 84.959739685058594
   }
}
