{
   "asset" : {
      "generator" : "osg2cesiumApp",
      "version" : "1.0"
   },
   "root" : {
      "boundingVolume" : {
         "box" : [
            82.375,
            -77.125,
            -101.47959136962891,
            9.4375152587890625,
            0.0,
            0.0,
            0.0,
            9.4375152587890625,
            0.0,
            0.0,
            0.0,
            4.6145172119140625
         ]
      },
      "content" : {
         "uri" : "Tile_+002_+002_L21_0002100.b3dm"
      },
      "geometricError" : 0.69781112670898438
   }
}
