{
   "asset" : {
      "generator" : "osg2cesiumApp",
      "version" : "1.0"
   },
   "root" : {
      "boundingVolume" : {
         "box" : [
            -92.873916625976563,
            -365.14703369140625,
            -97.813034057617188,
            15.998943328857422,
            0.0,
            0.0,
            0.0,
            18.354415893554688,
            0.0,
            0.0,
            0.0,
            7.1581192016601563
         ]
      },
      "children" : [
         {
            "boundingVolume" : {
               "box" : [
                  -100.060302734375,
                  -374.26171875,
                  -98.198860168457031,
                  4.3728179931640625,
                  0.0,
                  0.0,
                  0.0,
                  9.177215576171875,
                  0.0,
                  0.0,
                  0.0,
                  6.2360000610351563
               ]
            },
            "content" : {
               "uri" : "Tile_+001_+000_L21_0000200.json"
            },
            "geometricError" : 0.58869963884353638
         },
         {
            "boundingVolume" : {
               "box" : [
                  -102.275634765625,
                  -356.03231811523438,
                  -100.41262817382813,
                  6.5881500244140625,
                  0.0,
                  0.0,
                  0.0,
                  9.177215576171875,
                  0.0,
                  0.0,
                  0.0,
                  3.6607398986816406
               ]
            },
            "content" : {
               "uri" : "Tile_+001_+000_L21_0000210.json"
            },
            "geometricError" : 0.58869963884353638
         },
         {
            "boundingVolume" : {
               "box" : [
                  -86.375,
                  -374.26171875,
                  -98.35748291015625,
                  9.4375152587890625,
                  0.0,
                  0.0,
                  0.0,
                  9.177215576171875,
                  0.0,
                  0.0,
                  0.0,
                  6.6114768981933594
               ]
            },
            "content" : {
               "uri" : "Tile_+001_+000_L21_0000220.json"
            },
            "geometricError" : 0.58869963884353638
         },
         {
            "boundingVolume" : {
               "box" : [
                  -86.375,
                  -356.03231811523438,
                  -97.731254577636719,
                  9.4375152587890625,
                  0.0,
                  0.0,
                  0.0,
                  9.177215576171875,
                  0.0,
                  0.0,
                  0.0,
                  7.1128158569335938
               ]
            },
            "content" : {
               "uri" : "Tile_+001_+000_L21_0000230.json"
            },
            "geometricError" : 0.58869963884353638
         }
      ],
      "content" : {
         "uri" : "Tile_+001_+000_L20_000020t3.b3dm"
      },
      "geometricError" : 1.1773992776870728
   }
}
