{
   "asset" : {
      "generator" : "osg2cesiumApp",
      "version" : "1.0"
   },
   "root" : {
      "boundingVolume" : {
         "box" : [
            -105.125,
            -282.7352294921875,
            -92.89483642578125,
            9.4062576293945313,
            0.0,
            0.0,
            0.0,
            9.5254058837890625,
            0.0,
            0.0,
            0.0,
            13.403301239013672
         ]
      },
      "content" : {
         "uri" : "Tile_+001_+000_L22_00013100.b3dm"
      },
      "geometricError" : 0.4655202329158783
   }
}
