{
   "asset" : {
      "generator" : "osg2cesiumApp",
      "version" : "1.0"
   },
   "root" : {
      "boundingVolume" : {
         "box" : [
            91.75,
            -142.41744995117188,
            -143.36428833007813,
            18.875022888183594,
            0.0,
            0.0,
            0.0,
            19.207588195800781,
            0.0,
            0.0,
            0.0,
            14.404129028320313
         ]
      },
      "children" : [
         {
            "boundingVolume" : {
               "box" : [
                  91.75,
                  -142.38618469238281,
                  -143.38638305664063,
                  18.812515258789063,
                  0.0,
                  0.0,
                  0.0,
                  19.17633056640625,
                  0.0,
                  0.0,
                  0.0,
                  14.363716125488281
               ]
            },
            "content" : {
               "uri" : "Tile_+002_+001_L21_0003200.json"
            },
            "geometricError" : 1.4991167783737183
         }
      ],
      "content" : {
         "uri" : "Tile_+002_+001_L20_000320.b3dm"
      },
      "geometricError" : 2.9982335567474365
   }
}
